mlserver_catboost/__init__.py
mlserver_catboost/catboost.py
mlserver_catboost/version.py
mlserver_catboost-1.7.1.dist-info/LICENSE
mlserver_catboost-1.7.1.dist-info/METADATA
mlserver_catboost-1.7.1.dist-info/WHEEL
mlserver_catboost-1.7.1.dist-info/RECORD
