Metadata-Version: 2.3
Name: mlserver-catboost
Version: 1.7.1
Summary: Catboost runtime for MLServer
License: Apache-2.0
Author: Theofilos Papapanagiotou
Author-email: theofilos@gmail.com
Maintainer: Seldon Technologies Ltd.
Maintainer-email: hello@seldon.io
Requires-Python: >=3.9,<3.13
Classifier: License :: OSI Approved :: Apache Software License
Classifier: Programming Language :: Python :: 3
Classifier: Programming Language :: Python :: 3.9
Classifier: Programming Language :: Python :: 3.10
Classifier: Programming Language :: Python :: 3.11
Classifier: Programming Language :: Python :: 3.12
Requires-Dist: catboost
Requires-Dist: joblib
Requires-Dist: mlserver
